PupilPathApi/__init__.py
PupilPathApi-1.0.0.dist-info/METADATA
PupilPathApi-1.0.0.dist-info/WHEEL
PupilPathApi-1.0.0.dist-info/top_level.txt
PupilPathApi-1.0.0.dist-info/RECORD
