Metadata-Version: 2.1
Name: PupilPathApi
Version: 1.0.0
Summary: The one and only PupilPath api wrapper
Home-page: UNKNOWN
Author: Dark Studios
License: UNKNOWN
Platform: UNKNOWN
Requires-Dist: bs4
Requires-Dist: requests
